<?xml version="1.0" encoding="utf-8" ?>

<settings>
	<icon name="ICON_BACKSPACE"
		value="css:fas fa-backspace"
	/>
	<icon name="ICON_CODE_BRANCH"
		value="css:fas fa-code-branch"
	/>
	<icon name="ICON_EDIT"
		value="css:fas fa-edit"
	/>
	<icon name="ICON_FILE_DOWNLOAD"
		value="css:fas fa-file-download"
	/>
	<icon name="ICON_FILE_IMPORT"
		value="css:fas fa-file-import"
	/>
	<icon name="ICON_PLUS"
		value="css:fas fa-plus"
	/>
	<icon name="ICON_SHOE_PRINTS"
		value="css:fas fa-shoe-prints"
	/>
	<icon name="ICON_TRASH_ALT"
		value="css:fas fa-trash-alt"
	/>
</settings>