<?xml version="1.0" encoding="utf-8" ?>

<template>
	<params>
		<param name="viewName"
			value="searchInput"
		/>
		<param name="labelKey"
			value="tl.searchView.tabber"
		/>
		<param name="tabName"
			value="searchInput"
		/>
		<param name="renderer"
			optional="true"
		/>
	</params>

	<view class="com.top_logic.layout.component.configuration.CommandModelViewConfiguration"
		name="${viewName}"
		renderer="${renderer}"
	>
		<commandConfiguration class="com.top_logic.layout.component.configuration.TabSwitchCommandModelConfiguration"
			tabName="${tabName}"
		/>
	</view>
</template>